{
  "US48": {
    "latest": {
      "date": "2026-02-21",
      "updated": "2026-02-22 08:10",
      "renewables": {
        "megawatthours": 2471049,
        "gigawatthours": 2471,
        "percent": 24.85,
        "source": "Renewables"
      },
      "fossil_fuels": {
        "megawatthours": 5276475,
        "gigawatthours": 5276,
        "percent": 53.07,
        "source": "Fossil Fuels"
      },
      "solar": {
        "megawatthours": 668385,
        "gigawatthours": 668,
        "percent": 6.72,
        "source": "Solar"
      },
      "wind": {
        "megawatthours": 1064992,
        "gigawatthours": 1065,
        "percent": 10.71,
        "source": "Wind"
      },
      "hydro": {
        "megawatthours": 709942,
        "gigawatthours": 710,
        "percent": 7.14,
        "source": "Hydro"
      },
      "nuclear": {
        "megawatthours": 2062608,
        "gigawatthours": 2063,
        "percent": 20.75,
        "source": "Nuclear"
      },
      "coal": {
        "megawatthours": 1538783,
        "gigawatthours": 1539,
        "percent": 15.48,
        "source": "Coal"
      },
      "natural_gas": {
        "megawatthours": 3731898,
        "gigawatthours": 3732,
        "percent": 37.54,
        "source": "Natural Gas"
      },
      "other": {
        "megawatthours": 165657,
        "gigawatthours": 166,
        "percent": 1.67,
        "source": "Other"
      }
    },
    "history": {
      "total": [
        {
          "date": "2026-02-09",
          "megawatthours": 12055773,
          "gigawatthours": 12056
        },
        {
          "date": "2026-02-10",
          "megawatthours": 11291349,
          "gigawatthours": 11291
        },
        {
          "date": "2026-02-11",
          "megawatthours": 11117113,
          "gigawatthours": 11117
        },
        {
          "date": "2026-02-12",
          "megawatthours": 11356107,
          "gigawatthours": 11356
        },
        {
          "date": "2026-02-13",
          "megawatthours": 11234110,
          "gigawatthours": 11234
        },
        {
          "date": "2026-02-14",
          "megawatthours": 10595514,
          "gigawatthours": 10596
        },
        {
          "date": "2026-02-15",
          "megawatthours": 10291646,
          "gigawatthours": 10292
        },
        {
          "date": "2026-02-16",
          "megawatthours": 10983821,
          "gigawatthours": 10984
        },
        {
          "date": "2026-02-17",
          "megawatthours": 11085495,
          "gigawatthours": 11085
        },
        {
          "date": "2026-02-18",
          "megawatthours": 10868721,
          "gigawatthours": 10869
        },
        {
          "date": "2026-02-19",
          "megawatthours": 10166199,
          "gigawatthours": 10166
        },
        {
          "date": "2026-02-20",
          "megawatthours": 10293799,
          "gigawatthours": 10294
        },
        {
          "date": "2026-02-21",
          "megawatthours": 9887760,
          "gigawatthours": 9888
        }
      ]
    }
  },
  "CISO": {
    "latest": {
      "date": "2026-02-21",
      "updated": "2026-02-22 08:10",
      "renewables": {
        "megawatthours": 211687,
        "gigawatthours": 212,
        "percent": 58.1,
        "source": "Renewables"
      },
      "fossil_fuels": {
        "megawatthours": 117864,
        "gigawatthours": 118,
        "percent": 32.35,
        "source": "Fossil Fuels"
      },
      "solar": {
        "megawatthours": 129907,
        "gigawatthours": 130,
        "percent": 35.66,
        "source": "Solar"
      },
      "wind": {
        "megawatthours": 11275,
        "gigawatthours": 11,
        "percent": 3.09,
        "source": "Wind"
      },
      "hydro": {
        "megawatthours": 53574,
        "gigawatthours": 54,
        "percent": 14.7,
        "source": "Hydro"
      },
      "nuclear": {
        "megawatthours": 40103,
        "gigawatthours": 40,
        "percent": 11.01,
        "source": "Nuclear"
      },
      "coal": {
        "megawatthours": 0,
        "gigawatthours": 0,
        "percent": 0.0,
        "source": "Coal"
      },
      "natural_gas": {
        "megawatthours": 117911,
        "gigawatthours": 118,
        "percent": 32.36,
        "source": "Natural Gas"
      },
      "other": {
        "megawatthours": 16931,
        "gigawatthours": 17,
        "percent": 4.65,
        "source": "Other"
      }
    },
    "history": {
      "total": [
        {
          "date": "2026-02-08",
          "megawatthours": 305244,
          "gigawatthours": 305
        },
        {
          "date": "2026-02-09",
          "megawatthours": 326397,
          "gigawatthours": 326
        },
        {
          "date": "2026-02-10",
          "megawatthours": 386135,
          "gigawatthours": 386
        },
        {
          "date": "2026-02-11",
          "megawatthours": 390723,
          "gigawatthours": 391
        },
        {
          "date": "2026-02-12",
          "megawatthours": 385833,
          "gigawatthours": 386
        },
        {
          "date": "2026-02-13",
          "megawatthours": 387287,
          "gigawatthours": 387
        },
        {
          "date": "2026-02-14",
          "megawatthours": 322182,
          "gigawatthours": 322
        },
        {
          "date": "2026-02-15",
          "megawatthours": 328797,
          "gigawatthours": 329
        },
        {
          "date": "2026-02-16",
          "megawatthours": 365922,
          "gigawatthours": 366
        },
        {
          "date": "2026-02-17",
          "megawatthours": 403004,
          "gigawatthours": 403
        },
        {
          "date": "2026-02-18",
          "megawatthours": 400413,
          "gigawatthours": 400
        },
        {
          "date": "2026-02-19",
          "megawatthours": 448749,
          "gigawatthours": 449
        },
        {
          "date": "2026-02-20",
          "megawatthours": 425312,
          "gigawatthours": 425
        },
        {
          "date": "2026-02-21",
          "megawatthours": 358417,
          "gigawatthours": 358
        }
      ]
    }
  },
  "MISO": {
    "latest": {
      "date": "2026-02-21",
      "updated": "2026-02-22 08:10",
      "renewables": {
        "megawatthours": 452667,
        "gigawatthours": 453,
        "percent": 25.23,
        "source": "Renewables"
      },
      "fossil_fuels": {
        "megawatthours": 1101029,
        "gigawatthours": 1101,
        "percent": 61.37,
        "source": "Fossil Fuels"
      },
      "solar": {
        "megawatthours": 72374,
        "gigawatthours": 72,
        "percent": 4.03,
        "source": "Solar"
      },
      "wind": {
        "megawatthours": 360206,
        "gigawatthours": 360,
        "percent": 20.08,
        "source": "Wind"
      },
      "hydro": {
        "megawatthours": 20087,
        "gigawatthours": 20,
        "percent": 1.12,
        "source": "Hydro"
      },
      "nuclear": {
        "megawatthours": 232395,
        "gigawatthours": 232,
        "percent": 12.95,
        "source": "Nuclear"
      },
      "coal": {
        "megawatthours": 506216,
        "gigawatthours": 506,
        "percent": 28.21,
        "source": "Coal"
      },
      "natural_gas": {
        "megawatthours": 594813,
        "gigawatthours": 595,
        "percent": 33.15,
        "source": "Natural Gas"
      },
      "other": {
        "megawatthours": 8113,
        "gigawatthours": 8,
        "percent": 0.45,
        "source": "Other"
      }
    },
    "history": {
      "total": [
        {
          "date": "2026-02-09",
          "megawatthours": 1930946,
          "gigawatthours": 1931
        },
        {
          "date": "2026-02-10",
          "megawatthours": 1834328,
          "gigawatthours": 1834
        },
        {
          "date": "2026-02-11",
          "megawatthours": 1792250,
          "gigawatthours": 1792
        },
        {
          "date": "2026-02-12",
          "megawatthours": 1812608,
          "gigawatthours": 1813
        },
        {
          "date": "2026-02-13",
          "megawatthours": 1757607,
          "gigawatthours": 1758
        },
        {
          "date": "2026-02-14",
          "megawatthours": 1632038,
          "gigawatthours": 1632
        },
        {
          "date": "2026-02-15",
          "megawatthours": 1618064,
          "gigawatthours": 1618
        },
        {
          "date": "2026-02-16",
          "megawatthours": 1744967,
          "gigawatthours": 1745
        },
        {
          "date": "2026-02-17",
          "megawatthours": 1771527,
          "gigawatthours": 1772
        },
        {
          "date": "2026-02-18",
          "megawatthours": 1725882,
          "gigawatthours": 1726
        },
        {
          "date": "2026-02-19",
          "megawatthours": 1768868,
          "gigawatthours": 1769
        },
        {
          "date": "2026-02-20",
          "megawatthours": 1818302,
          "gigawatthours": 1818
        },
        {
          "date": "2026-02-21",
          "megawatthours": 1799341,
          "gigawatthours": 1799
        }
      ]
    }
  },
  "ERCO": {
    "latest": {
      "date": "2026-02-21",
      "updated": "2026-02-22 08:10",
      "renewables": {
        "megawatthours": 552149,
        "gigawatthours": 552,
        "percent": 47.38,
        "source": "Renewables"
      },
      "fossil_fuels": {
        "megawatthours": 489520,
        "gigawatthours": 490,
        "percent": 42.01,
        "source": "Fossil Fuels"
      },
      "solar": {
        "megawatthours": 174966,
        "gigawatthours": 175,
        "percent": 15.01,
        "source": "Solar"
      },
      "wind": {
        "megawatthours": 376824,
        "gigawatthours": 377,
        "percent": 32.33,
        "source": "Wind"
      },
      "hydro": {
        "megawatthours": 359,
        "gigawatthours": 0,
        "percent": 0.03,
        "source": "Hydro"
      },
      "nuclear": {
        "megawatthours": 122389,
        "gigawatthours": 122,
        "percent": 10.5,
        "source": "Nuclear"
      },
      "coal": {
        "megawatthours": 137621,
        "gigawatthours": 138,
        "percent": 11.81,
        "source": "Coal"
      },
      "natural_gas": {
        "megawatthours": 351899,
        "gigawatthours": 352,
        "percent": 30.2,
        "source": "Natural Gas"
      },
      "other": {
        "megawatthours": 1321,
        "gigawatthours": 1,
        "percent": 0.11,
        "source": "Other"
      }
    },
    "history": {
      "total": [
        {
          "date": "2026-02-08",
          "megawatthours": 1100513,
          "gigawatthours": 1101
        },
        {
          "date": "2026-02-09",
          "megawatthours": 1150582,
          "gigawatthours": 1151
        },
        {
          "date": "2026-02-10",
          "megawatthours": 1144868,
          "gigawatthours": 1145
        },
        {
          "date": "2026-02-11",
          "megawatthours": 1150257,
          "gigawatthours": 1150
        },
        {
          "date": "2026-02-12",
          "megawatthours": 1168963,
          "gigawatthours": 1169
        },
        {
          "date": "2026-02-13",
          "megawatthours": 1172946,
          "gigawatthours": 1173
        },
        {
          "date": "2026-02-14",
          "megawatthours": 1132313,
          "gigawatthours": 1132
        },
        {
          "date": "2026-02-15",
          "megawatthours": 1090269,
          "gigawatthours": 1090
        },
        {
          "date": "2026-02-16",
          "megawatthours": 1165282,
          "gigawatthours": 1165
        },
        {
          "date": "2026-02-17",
          "megawatthours": 1183412,
          "gigawatthours": 1183
        },
        {
          "date": "2026-02-18",
          "megawatthours": 1180971,
          "gigawatthours": 1181
        },
        {
          "date": "2026-02-19",
          "megawatthours": 1193998,
          "gigawatthours": 1194
        },
        {
          "date": "2026-02-20",
          "megawatthours": 1193817,
          "gigawatthours": 1194
        },
        {
          "date": "2026-02-21",
          "megawatthours": 1167043,
          "gigawatthours": 1167
        }
      ]
    }
  },
  "PJM": {
    "latest": {
      "date": "2026-02-21",
      "updated": "2026-02-22 08:10",
      "renewables": {
        "megawatthours": 174309,
        "gigawatthours": 174,
        "percent": 7.56,
        "source": "Renewables"
      },
      "fossil_fuels": {
        "megawatthours": 1342630,
        "gigawatthours": 1343,
        "percent": 58.24,
        "source": "Fossil Fuels"
      },
      "solar": {
        "megawatthours": 51244,
        "gigawatthours": 51,
        "percent": 2.22,
        "source": "Solar"
      },
      "wind": {
        "megawatthours": 92733,
        "gigawatthours": 93,
        "percent": 4.02,
        "source": "Wind"
      },
      "hydro": {
        "megawatthours": 30332,
        "gigawatthours": 30,
        "percent": 1.32,
        "source": "Hydro"
      },
      "nuclear": {
        "megawatthours": 751770,
        "gigawatthours": 752,
        "percent": 32.61,
        "source": "Nuclear"
      },
      "coal": {
        "megawatthours": 354861,
        "gigawatthours": 355,
        "percent": 15.39,
        "source": "Coal"
      },
      "natural_gas": {
        "megawatthours": 983646,
        "gigawatthours": 984,
        "percent": 42.67,
        "source": "Natural Gas"
      },
      "other": {
        "megawatthours": 40638,
        "gigawatthours": 41,
        "percent": 1.76,
        "source": "Other"
      }
    },
    "history": {
      "total": [
        {
          "date": "2026-02-09",
          "megawatthours": 2940660,
          "gigawatthours": 2941
        },
        {
          "date": "2026-02-10",
          "megawatthours": 2616230,
          "gigawatthours": 2616
        },
        {
          "date": "2026-02-11",
          "megawatthours": 2572165,
          "gigawatthours": 2572
        },
        {
          "date": "2026-02-12",
          "megawatthours": 2676864,
          "gigawatthours": 2677
        },
        {
          "date": "2026-02-13",
          "megawatthours": 2634003,
          "gigawatthours": 2634
        },
        {
          "date": "2026-02-14",
          "megawatthours": 2410718,
          "gigawatthours": 2411
        },
        {
          "date": "2026-02-15",
          "megawatthours": 2326889,
          "gigawatthours": 2327
        },
        {
          "date": "2026-02-16",
          "megawatthours": 2468370,
          "gigawatthours": 2468
        },
        {
          "date": "2026-02-17",
          "megawatthours": 2435102,
          "gigawatthours": 2435
        },
        {
          "date": "2026-02-18",
          "megawatthours": 2369190,
          "gigawatthours": 2369
        },
        {
          "date": "2026-02-19",
          "megawatthours": 2370149,
          "gigawatthours": 2370
        },
        {
          "date": "2026-02-20",
          "megawatthours": 2396106,
          "gigawatthours": 2396
        },
        {
          "date": "2026-02-21",
          "megawatthours": 2306429,
          "gigawatthours": 2306
        }
      ]
    }
  },
  "NYIS": {
    "latest": {
      "date": "2026-02-21",
      "updated": "2026-02-22 08:10",
      "renewables": {
        "megawatthours": 69717,
        "gigawatthours": 70,
        "percent": 19.63,
        "source": "Renewables"
      },
      "fossil_fuels": {
        "megawatthours": 201705,
        "gigawatthours": 202,
        "percent": 56.8,
        "source": "Fossil Fuels"
      },
      "solar": {
        "megawatthours": 0,
        "gigawatthours": 0,
        "percent": 0.0,
        "source": "Solar"
      },
      "wind": {
        "megawatthours": 9006,
        "gigawatthours": 9,
        "percent": 2.54,
        "source": "Wind"
      },
      "hydro": {
        "megawatthours": 60711,
        "gigawatthours": 61,
        "percent": 17.1,
        "source": "Hydro"
      },
      "nuclear": {
        "megawatthours": 78806,
        "gigawatthours": 79,
        "percent": 22.19,
        "source": "Nuclear"
      },
      "coal": {
        "megawatthours": 0,
        "gigawatthours": 0,
        "percent": 0.0,
        "source": "Coal"
      },
      "natural_gas": {
        "megawatthours": 201705,
        "gigawatthours": 202,
        "percent": 56.8,
        "source": "Natural Gas"
      },
      "other": {
        "megawatthours": 4906,
        "gigawatthours": 5,
        "percent": 1.38,
        "source": "Other"
      }
    },
    "history": {
      "total": [
        {
          "date": "2026-02-09",
          "megawatthours": 454069,
          "gigawatthours": 454
        },
        {
          "date": "2026-02-10",
          "megawatthours": 412817,
          "gigawatthours": 413
        },
        {
          "date": "2026-02-11",
          "megawatthours": 409233,
          "gigawatthours": 409
        },
        {
          "date": "2026-02-12",
          "megawatthours": 403287,
          "gigawatthours": 403
        },
        {
          "date": "2026-02-13",
          "megawatthours": 386618,
          "gigawatthours": 387
        },
        {
          "date": "2026-02-14",
          "megawatthours": 360470,
          "gigawatthours": 360
        },
        {
          "date": "2026-02-15",
          "megawatthours": 346063,
          "gigawatthours": 346
        },
        {
          "date": "2026-02-16",
          "megawatthours": 367829,
          "gigawatthours": 368
        },
        {
          "date": "2026-02-17",
          "megawatthours": 367824,
          "gigawatthours": 368
        },
        {
          "date": "2026-02-18",
          "megawatthours": 372127,
          "gigawatthours": 372
        },
        {
          "date": "2026-02-19",
          "megawatthours": 365235,
          "gigawatthours": 365
        },
        {
          "date": "2026-02-20",
          "megawatthours": 381398,
          "gigawatthours": 381
        },
        {
          "date": "2026-02-21",
          "megawatthours": 354679,
          "gigawatthours": 355
        }
      ]
    }
  },
  "ISNE": {
    "latest": {
      "date": "2026-02-21",
      "updated": "2026-02-22 08:10",
      "renewables": {
        "megawatthours": 26165,
        "gigawatthours": 26,
        "percent": 8.73,
        "source": "Renewables"
      },
      "fossil_fuels": {
        "megawatthours": 168868,
        "gigawatthours": 169,
        "percent": 56.32,
        "source": "Fossil Fuels"
      },
      "solar": {
        "megawatthours": 2479,
        "gigawatthours": 2,
        "percent": 0.83,
        "source": "Solar"
      },
      "wind": {
        "megawatthours": 12880,
        "gigawatthours": 13,
        "percent": 4.3,
        "source": "Wind"
      },
      "hydro": {
        "megawatthours": 10806,
        "gigawatthours": 11,
        "percent": 3.6,
        "source": "Hydro"
      },
      "nuclear": {
        "megawatthours": 88052,
        "gigawatthours": 88,
        "percent": 29.37,
        "source": "Nuclear"
      },
      "coal": {
        "megawatthours": 58,
        "gigawatthours": 0,
        "percent": 0.02,
        "source": "Coal"
      },
      "natural_gas": {
        "megawatthours": 168677,
        "gigawatthours": 169,
        "percent": 56.26,
        "source": "Natural Gas"
      },
      "other": {
        "megawatthours": 16873,
        "gigawatthours": 17,
        "percent": 5.63,
        "source": "Other"
      }
    },
    "history": {
      "total": [
        {
          "date": "2026-02-08",
          "megawatthours": 375985,
          "gigawatthours": 376
        },
        {
          "date": "2026-02-09",
          "megawatthours": 371405,
          "gigawatthours": 371
        },
        {
          "date": "2026-02-10",
          "megawatthours": 339419,
          "gigawatthours": 339
        },
        {
          "date": "2026-02-11",
          "megawatthours": 333898,
          "gigawatthours": 334
        },
        {
          "date": "2026-02-12",
          "megawatthours": 308710,
          "gigawatthours": 309
        },
        {
          "date": "2026-02-13",
          "megawatthours": 305582,
          "gigawatthours": 306
        },
        {
          "date": "2026-02-14",
          "megawatthours": 305199,
          "gigawatthours": 305
        },
        {
          "date": "2026-02-15",
          "megawatthours": 287343,
          "gigawatthours": 287
        },
        {
          "date": "2026-02-16",
          "megawatthours": 298417,
          "gigawatthours": 298
        },
        {
          "date": "2026-02-17",
          "megawatthours": 310802,
          "gigawatthours": 311
        },
        {
          "date": "2026-02-18",
          "megawatthours": 312623,
          "gigawatthours": 313
        },
        {
          "date": "2026-02-19",
          "megawatthours": 285113,
          "gigawatthours": 285
        },
        {
          "date": "2026-02-20",
          "megawatthours": 314790,
          "gigawatthours": 315
        },
        {
          "date": "2026-02-21",
          "megawatthours": 300245,
          "gigawatthours": 300
        }
      ]
    }
  },
  "SWPP": {
    "latest": {
      "date": "2026-02-19",
      "updated": "2026-02-22 08:10",
      "renewables": {
        "megawatthours": 417125,
        "gigawatthours": 417,
        "percent": 56.26,
        "source": "Renewables"
      },
      "fossil_fuels": {
        "megawatthours": 274515,
        "gigawatthours": 275,
        "percent": 37.03,
        "source": "Fossil Fuels"
      },
      "solar": {
        "megawatthours": 0,
        "gigawatthours": 0,
        "percent": 0.0,
        "source": "Solar"
      },
      "wind": {
        "megawatthours": 399845,
        "gigawatthours": 400,
        "percent": 53.93,
        "source": "Wind"
      },
      "hydro": {
        "megawatthours": 17280,
        "gigawatthours": 17,
        "percent": 2.33,
        "source": "Hydro"
      },
      "nuclear": {
        "megawatthours": 48779,
        "gigawatthours": 49,
        "percent": 6.58,
        "source": "Nuclear"
      },
      "coal": {
        "megawatthours": 131673,
        "gigawatthours": 132,
        "percent": 17.76,
        "source": "Coal"
      },
      "natural_gas": {
        "megawatthours": 142842,
        "gigawatthours": 143,
        "percent": 19.27,
        "source": "Natural Gas"
      },
      "other": {
        "megawatthours": 1008,
        "gigawatthours": 1,
        "percent": 0.14,
        "source": "Other"
      }
    },
    "history": {
      "total": [
        {
          "date": "2026-02-09",
          "megawatthours": 805574,
          "gigawatthours": 806
        },
        {
          "date": "2026-02-10",
          "megawatthours": 777788,
          "gigawatthours": 778
        },
        {
          "date": "2026-02-11",
          "megawatthours": 765149,
          "gigawatthours": 765
        },
        {
          "date": "2026-02-12",
          "megawatthours": 778865,
          "gigawatthours": 779
        },
        {
          "date": "2026-02-13",
          "megawatthours": 758732,
          "gigawatthours": 759
        },
        {
          "date": "2026-02-14",
          "megawatthours": 731099,
          "gigawatthours": 731
        },
        {
          "date": "2026-02-15",
          "megawatthours": 715451,
          "gigawatthours": 715
        },
        {
          "date": "2026-02-16",
          "megawatthours": 795114,
          "gigawatthours": 795
        },
        {
          "date": "2026-02-17",
          "megawatthours": 808694,
          "gigawatthours": 809
        },
        {
          "date": "2026-02-18",
          "megawatthours": 741427,
          "gigawatthours": 741
        },
        {
          "date": "2026-02-19",
          "megawatthours": 741427,
          "gigawatthours": 741
        }
      ]
    }
  }
}